Metadata-Version: 2.4
Name: t_record_lib
Version: 0.3.0
Summary: Cookiecutter template for Thoughtful pip package
Home-page: https://www.thoughtful.ai/
Author: Thoughtful
Author-email: support@thoughtful.ai
Keywords: t_record
Classifier: Intended Audience :: Developers
Classifier: Natural Language :: English
Classifier: Programming Language :: Python :: 3
Classifier: Programming Language :: Python :: 3.11
Requires-Python: >=3.11
Requires-Dist: t-bug-catcher>=0.1.0
Requires-Dist: t-object~=0.1.0
Requires-Dist: t-utils-kit~=0.1.0
Requires-Dist: jinja2>=3.0.0
Dynamic: author
Dynamic: author-email
Dynamic: classifier
Dynamic: description
Dynamic: home-page
Dynamic: keywords
Dynamic: requires-dist
Dynamic: requires-python
Dynamic: summary
